environments/__init__.py
environments/core.py
environments/utils.py
blueprint_environments-0.1.2.dist-info/METADATA
blueprint_environments-0.1.2.dist-info/WHEEL
blueprint_environments-0.1.2.dist-info/RECORD
