Metadata-Version: 2.1
Name: blueprint-environments
Version: 0.1.2
Summary: Set of tools to manage environments
Author: Carlo G
Author-email: carlo.rafael@hotmail.com
Requires-Python: >=3.8,<4.0
Classifier: Programming Language :: Python :: 3
Classifier: Programming Language :: Python :: 3.8
Classifier: Programming Language :: Python :: 3.9
Classifier: Programming Language :: Python :: 3.10
Classifier: Programming Language :: Python :: 3.11
Classifier: Programming Language :: Python :: 3.12
Requires-Dist: pyyaml (>=6.0,<7.0)
